hygiene/__init__.py
hygiene/singleton.py
hygiene/payload/__init__.py
hygiene/payload/boxing/__init__.py
hygiene/payload/boxing/boxing.py
hygiene/tests/test.py
hygiene/util/__init__.py
hygiene/util/builders/__init__.py
hygiene/util/builders/csv.py
hygiene/util/common/__init__.py
hygiene/util/common/helpers/__init__.py
hygiene/util/common/helpers/_csv.py
hygiene/util/formatters/__init__.py
hygiene/util/formatters/single/__init__.py
hygiene/util/formatters/single/csv.py
hygiene/util/formatters/single/json.py
hygiene/util/formatters/single/yaml.py
hygiene_dm-0.0.6.dist-info/LICENSE
hygiene_dm-0.0.6.dist-info/METADATA
hygiene_dm-0.0.6.dist-info/WHEEL
hygiene_dm-0.0.6.dist-info/top_level.txt
hygiene_dm-0.0.6.dist-info/RECORD
