Metadata-Version: 2.1
Name: hygiene-dm
Version: 0.0.6
Summary: hygiene (🪥) is a data preprocessing toolkit that makes it easy to create common LLM-related data structures; from training data to chain payloads!
Home-page: https://github.com/DylanAlloy/hygiene
License-File: LICENSE
